wpypress/__init__.py
wpypress/auth.py
wpypress/client.py
wpypress/utils.py
wpypress/endpoints/__init__.py
wpypress/endpoints/categories.py
wpypress/endpoints/media.py
wpypress/endpoints/pages.py
wpypress/endpoints/posts.py
wpypress/endpoints/seo.py
wpypress/endpoints/tags.py
wpypress-0.1.3.dist-info/LICENSE
wpypress-0.1.3.dist-info/METADATA
wpypress-0.1.3.dist-info/WHEEL
wpypress-0.1.3.dist-info/top_level.txt
wpypress-0.1.3.dist-info/RECORD
