Metadata-Version: 2.1
Name: wpypress
Version: 0.1.3
Summary: A versatile Python library for seamless interaction with the WordPress REST API, including built-in SEO features and more.
Home-page: https://github.com/EugenioPetulla/wpypress
Author: Eugenio Petullà
Author-email: eugenio@codeat.it
Classifier: Programming Language :: Python :: 3
Classifier: License :: OSI Approved :: MIT License
Classifier: Operating System :: OS Independent
Requires-Python: >=3.6
License-File: LICENSE
Requires-Dist: requests>=2.25.1
